pycrobit.py
pycrobit-0.2.0.dist-info/LICENSE
pycrobit-0.2.0.dist-info/METADATA
pycrobit-0.2.0.dist-info/WHEEL
pycrobit-0.2.0.dist-info/top_level.txt
pycrobit-0.2.0.dist-info/RECORD
