Metadata-Version: 2.1
Name: pycrobit
Version: 0.2.0
Summary: Recycle microbits exercises in python using 5 * 5 strings and some coloring
Home-page: https://github.com/MixTeen/pycrobit
Author: Pierre Sassoulas
Author-email: pierre.sassoulas@gmail.com
License: MIT
Classifier: Intended Audience :: Developers
Classifier: License :: OSI Approved :: MIT License
Classifier: Operating System :: OS Independent
Classifier: Programming Language :: Python :: 3
License-File: LICENSE
Provides-Extra: colorama
Requires-Dist: colorama ; extra == 'colorama'
Provides-Extra: test
Requires-Dist: coverage ; extra == 'test'
Requires-Dist: coveralls ; extra == 'test'
Requires-Dist: pre-commit ; extra == 'test'
Requires-Dist: pylint (==2.14.0b1) ; extra == 'test'
Requires-Dist: pytest-cov ; extra == 'test'
Requires-Dist: pytest-vcr ; extra == 'test'
Requires-Dist: python-coveralls ; extra == 'test'
